[
  {
    "id": 1,
    "type": 5,
    "specialty": 2,
    "sleepType": 4,
    "stats": {
      "frequency": 4400,
      "maxCarry": 11,
      "friendshipPoints": 5,
      "recruit": {
        "exp": 18,
        "shards": 39
      }
    },
    "berry": {
      "id": 5,
      "quantity": 1
    },
    "ingredientChain": 3,
    "skill": 10,
    "evolution": {
      "next": [
        {
          "id": 2,
          "conditions": [
            {
              "type": "candy",
              "count": 40
            },
            {
              "type": "level",
              "level": 12
            }
          ]
        }
      ],
      "stage": 1,
      "previous": null
    },
    "expType": 1,
    "eventType": 1
  },
  {
    "id": 2,
    "type": 5,
    "specialty": 2,
    "sleepType": 4,
    "stats": {
      "frequency": 3300,
      "maxCarry": 14,
      "friendshipPoints": 12,
      "recruit": {
        "exp": 116,
        "shards": 245
      }
    },
    "berry": {
      "id": 5,
      "quantity": 1
    },
    "ingredientChain": 3,
    "skill": 10,
    "evolution": {
      "next": [
        {
          "id": 3,
          "conditions": [
            {
              "type": "candy",
              "count": 80
            },
            {
              "type": "level",
              "level": 24
            }
          ]
        }
      ],
      "stage": 2,
      "previous": 1
    },
    "expType": 1,
    "eventType": 1
  },
  {
    "id": 3,
    "type": 5,
    "specialty": 2,
    "sleepType": 4,
    "stats": {
      "frequency": 2800,
      "maxCarry": 17,
      "friendshipPoints": 20,
      "recruit": {
        "exp": 574,
        "shards": 1033
      }
    },
    "berry": {
      "id": 5,
      "quantity": 1
    },
    "ingredientChain": 3,
    "skill": 10,
    "evolution": {
      "next": [],
      "stage": 3,
      "previous": 2
    },
    "expType": 1,
    "eventType": 1
  },
  {
    "id": 4,
    "type": 2,
    "specialty": 2,
    "sleepType": 1,
    "stats": {
      "frequency": 3500,
      "maxCarry": 12,
      "friendshipPoints": 5,
      "recruit": {
        "exp": 16,
        "shards": 42
      }
    },
    "berry": {
      "id": 2,
      "quantity": 1
    },
    "ingredientChain": 6,
    "skill": 10,
    "evolution": {
      "next": [
        {
          "id": 5,
          "conditions": [
            {
              "type": "candy",
              "count": 40
            },
            {
              "type": "level",
              "level": 12
            }
          ]
        }
      ],
      "stage": 1,
      "previous": null
    },
    "expType": 1,
    "eventType": 1
  },
  {
    "id": 5,
    "type": 2,
    "specialty": 2,
    "sleepType": 1,
    "stats": {
      "frequency": 3000,
      "maxCarry": 15,
      "friendshipPoints": 12,
      "recruit": {
        "exp": 116,
        "shards": 245
      }
    },
    "berry": {
      "id": 2,
      "quantity": 1
    },
    "ingredientChain": 6,
    "skill": 10,
    "evolution": {
      "next": [
        {
          "id": 6,
          "conditions": [
            {
              "type": "candy",
              "count": 80
            },
            {
              "type": "level",
              "level": 27
            }
          ]
        }
      ],
      "stage": 2,
      "previous": 4
    },
    "expType": 1,
    "eventType": 1
  },
  {
    "id": 6,
    "type": 2,
    "specialty": 2,
    "sleepType": 1,
    "stats": {
      "frequency": 2400,
      "maxCarry": 19,
      "friendshipPoints": 20,
      "recruit": {
        "exp": 528,
        "shards": 1116
      }
    },
    "berry": {
      "id": 2,
      "quantity": 1
    },
    "ingredientChain": 6,
    "skill": 10,
    "evolution": {
      "next": [],
      "stage": 3,
      "previous": 5
    },
    "expType": 1,
    "eventType": 1
  },
  {
    "id": 7,
    "type": 3,
    "specialty": 2,
    "sleepType": 0,
    "stats": {
      "frequency": 4500,
      "maxCarry": 10,
      "friendshipPoints": 5,
      "recruit": {
        "exp": 18,
        "shards": 39
      }
    },
    "berry": {
      "id": 3,
      "quantity": 1
    },
    "ingredientChain": 9,
    "skill": 10,
    "evolution": {
      "next": [
        {
          "id": 8,
          "conditions": [
            {
              "type": "candy",
              "count": 40
            },
            {
              "type": "level",
              "level": 12
            }
          ]
        }
      ],
      "stage": 1,
      "previous": null
    },
    "expType": 1,
    "eventType": 1
  },
  {
    "id": 8,
    "type": 3,
    "specialty": 2,
    "sleepType": 0,
    "stats": {
      "frequency": 3400,
      "maxCarry": 14,
      "friendshipPoints": 12,
      "recruit": {
        "exp": 116,
        "shards": 245
      }
    },
    "berry": {
      "id": 3,
      "quantity": 1
    },
    "ingredientChain": 9,
    "skill": 10,
    "evolution": {
      "next": [
        {
          "id": 9,
          "conditions": [
            {
              "type": "candy",
              "count": 80
            },
            {
              "type": "level",
              "level": 27
            }
          ]
        }
      ],
      "stage": 2,
      "previous": 7
    },
    "expType": 1,
    "eventType": 1
  },
  {
    "id": 9,
    "type": 3,
    "specialty": 2,
    "sleepType": 0,
    "stats": {
      "frequency": 2800,
      "maxCarry": 17,
      "friendshipPoints": 20,
      "recruit": {
        "exp": 528,
        "shards": 1116
      }
    },
    "berry": {
      "id": 3,
      "quantity": 1
    },
    "ingredientChain": 9,
    "skill": 10,
    "evolution": {
      "next": [],
      "stage": 3,
      "previous": 8
    },
    "expType": 1,
    "eventType": 1
  },
  {
    "id": 10,
    "type": 12,
    "specialty": 1,
    "sleepType": 4,
    "stats": {
      "frequency": 4400,
      "maxCarry": 11,
      "friendshipPoints": 5,
      "recruit": {
        "exp": 11,
        "shards": 12
      }
    },
    "berry": {
      "id": 12,
      "quantity": 2
    },
    "ingredientChain": 12,
    "skill": 10,
    "evolution": {
      "next": [
        {
          "id": 11,
          "conditions": [
            {
              "type": "candy",
              "count": 40
            },
            {
              "type": "level",
              "level": 5
            }
          ]
        }
      ],
      "stage": 1,
      "previous": null
    },
    "expType": 1,
    "eventType": 1
  },
  {
    "id": 11,
    "type": 12,
    "specialty": 1,
    "sleepType": 4,
    "stats": {
      "frequency": 4200,
      "maxCarry": 13,
      "friendshipPoints": 7,
      "recruit": {
        "exp": 29,
        "shards": 31
      }
    },
    "berry": {
      "id": 12,
      "quantity": 2
    },
    "ingredientChain": 12,
    "skill": 10,
    "evolution": {
      "next": [
        {
          "id": 12,
          "conditions": [
            {
              "type": "candy",
              "count": 80
            },
            {
              "type": "level",
              "level": 8
            }
          ]
        }
      ],
      "stage": 2,
      "previous": 10
    },
    "expType": 1,
    "eventType": 1
  },
  {
    "id": 12,
    "type": 12,
    "specialty": 1,
    "sleepType": 4,
    "stats": {
      "frequency": 2600,
      "maxCarry": 21,
      "friendshipPoints": 15,
      "recruit": {
        "exp": 397,
        "shards": 715
      }
    },
    "berry": {
      "id": 12,
      "quantity": 2
    },
    "ingredientChain": 12,
    "skill": 10,
    "evolution": {
      "next": [],
      "stage": 3,
      "previous": 11
    },
    "expType": 1,
    "eventType": 1
  },
  {
    "id": 19,
    "type": 1,
    "specialty": 1,
    "sleepType": 1,
    "stats": {
      "frequency": 4900,
      "maxCarry": 10,
      "friendshipPoints": 5,
      "recruit": {
        "exp": 7,
        "shards": 20
      }
    },
    "berry": {
      "id": 1,
      "quantity": 2
    },
    "ingredientChain": 20,
    "skill": 7,
    "evolution": {
      "next": [
        {
          "id": 20,
          "conditions": [
            {
              "type": "candy",
              "count": 40
            },
            {
              "type": "level",
              "level": 15
            }
          ]
        }
      ],
      "stage": 1,
      "previous": null
    },
    "expType": 1,
    "eventType": 1
  },
  {
    "id": 20,
    "type": 1,
    "specialty": 1,
    "sleepType": 1,
    "stats": {
      "frequency": 3200,
      "maxCarry": 16,
      "friendshipPoints": 12,
      "recruit": {
        "exp": 60,
        "shards": 155
      }
    },
    "berry": {
      "id": 1,
      "quantity": 2
    },
    "ingredientChain": 20,
    "skill": 7,
    "evolution": {
      "next": [],
      "stage": 2,
      "previous": 19
    },
    "expType": 1,
    "eventType": 1
  },
  {
    "id": 23,
    "type": 8,
    "specialty": 1,
    "sleepType": 4,
    "stats": {
      "frequency": 5000,
      "maxCarry": 10,
      "friendshipPoints": 5,
      "recruit": {
        "exp": 7,
        "shards": 19
      }
    },
    "berry": {
      "id": 8,
      "quantity": 2
    },
    "ingredientChain": 24,
    "skill": 7,
    "evolution": {
      "next": [
        {
          "id": 24,
          "conditions": [
            {
              "type": "candy",
              "count": 40
            },
            {
              "type": "level",
              "level": 17
            }
          ]
        }
      ],
      "stage": 1,
      "previous": null
    },
    "expType": 1,
    "eventType": 1
  },
  {
    "id": 24,
    "type": 8,
    "specialty": 1,
    "sleepType": 4,
    "stats": {
      "frequency": 3700,
      "maxCarry": 14,
      "friendshipPoints": 12,
      "recruit": {
        "exp": 103,
        "shards": 268
      }
    },
    "berry": {
      "id": 8,
      "quantity": 2
    },
    "ingredientChain": 24,
    "skill": 7,
    "evolution": {
      "next": [],
      "stage": 2,
      "previous": 23
    },
    "expType": 1,
    "eventType": 1
  },
  {
    "id": 25,
    "type": 4,
    "specialty": 1,
    "sleepType": 1,
    "stats": {
      "frequency": 2700,
      "maxCarry": 17,
      "friendshipPoints": 7,
      "recruit": {
        "exp": 7,
        "shards": 20
      }
    },
    "berry": {
      "id": 4,
      "quantity": 2
    },
    "ingredientChain": 26,
    "skill": 1,
    "evolution": {
      "next": [
        {
          "id": 26,
          "conditions": [
            {
              "type": "candy",
              "count": 80
            },
            {
              "type": "item",
              "item": 24,
              "count": 1
            }
          ]
        }
      ],
      "stage": 2,
      "previous": 172
    },
    "expType": 1,
    "eventType": 1
  },
  {
    "id": 26,
    "type": 4,
    "specialty": 1,
    "sleepType": 1,
    "stats": {
      "frequency": 2200,
      "maxCarry": 21,
      "friendshipPoints": 18,
      "recruit": {
        "exp": 326,
        "shards": 844
      }
    },
    "berry": {
      "id": 4,
      "quantity": 2
    },
    "ingredientChain": 26,
    "skill": 1,
    "evolution": {
      "next": [],
      "stage": 3,
      "previous": 25
    },
    "expType": 1,
    "eventType": 1
  },
  {
    "id": 35,
    "type": 18,
    "specialty": 1,
    "sleepType": 1,
    "stats": {
      "frequency": 4000,
      "maxCarry": 16,
      "friendshipPoints": 7,
      "recruit": {
        "exp": 49,
        "shards": 53
      }
    },
    "berry": {
      "id": 18,
      "quantity": 2
    },
    "ingredientChain": 173,
    "skill": 13,
    "evolution": {
      "next": [
        {
          "id": 36,
          "conditions": [
            {
              "type": "candy",
              "count": 80
            },
            {
              "type": "item",
              "item": 27,
              "count": 1
            }
          ]
        }
      ],
      "stage": 2,
      "previous": 173
    },
    "expType": 1,
    "eventType": 1
  },
  {
    "id": 36,
    "type": 18,
    "specialty": 1,
    "sleepType": 1,
    "stats": {
      "frequency": 2800,
      "maxCarry": 24,
      "friendshipPoints": 20,
      "recruit": {
        "exp": 677,
        "shards": 847
      }
    },
    "berry": {
      "id": 18,
      "quantity": 2
    },
    "ingredientChain": 173,
    "skill": 13,
    "evolution": {
      "next": [],
      "stage": 3,
      "previous": 35
    },
    "expType": 1,
    "eventType": 1
  },
  {
    "id": 39,
    "type": 18,
    "specialty": 3,
    "sleepType": 1,
    "stats": {
      "frequency": 3900,
      "maxCarry": 9,
      "friendshipPoints": 7,
      "recruit": {
        "exp": 23,
        "shards": 24
      }
    },
    "berry": {
      "id": 18,
      "quantity": 1
    },
    "ingredientChain": 40,
    "skill": 8,
    "evolution": {
      "next": [
        {
          "id": 40,
          "conditions": [
            {
              "type": "candy",
              "count": 80
            },
            {
              "type": "item",
              "item": 27,
              "count": 1
            }
          ]
        }
      ],
      "stage": 2,
      "previous": 174
    },
    "expType": 1,
    "eventType": 1
  },
  {
    "id": 40,
    "type": 18,
    "specialty": 3,
    "sleepType": 1,
    "stats": {
      "frequency": 2900,
      "maxCarry": 13,
      "friendshipPoints": 16,
      "recruit": {
        "exp": 253,
        "shards": 273
      }
    },
    "berry": {
      "id": 18,
      "quantity": 1
    },
    "ingredientChain": 40,
    "skill": 8,
    "evolution": {
      "next": [],
      "stage": 3,
      "previous": 39
    },
    "expType": 1,
    "eventType": 1
  },
  {
    "id": 50,
    "type": 9,
    "specialty": 2,
    "sleepType": 1,
    "stats": {
      "frequency": 4300,
      "maxCarry": 10,
      "friendshipPoints": 5,
      "recruit": {
        "exp": 7,
        "shards": 20
      }
    },
    "berry": {
      "id": 9,
      "quantity": 1
    },
    "ingredientChain": 51,
    "skill": 1,
    "evolution": {
      "next": [
        {
          "id": 51,
          "conditions": [
            {
              "type": "candy",
              "count": 40
            },
            {
              "type": "level",
              "level": 20
            }
          ]
        }
      ],
      "stage": 1,
      "previous": null
    },
    "expType": 1,
    "eventType": 1
  },
  {
    "id": 51,
    "type": 9,
    "specialty": 2,
    "sleepType": 1,
    "stats": {
      "frequency": 2800,
      "maxCarry": 16,
      "friendshipPoints": 12,
      "recruit": {
        "exp": 95,
        "shards": 284
      }
    },
    "berry": {
      "id": 9,
      "quantity": 1
    },
    "ingredientChain": 51,
    "skill": 1,
    "evolution": {
      "next": [],
      "stage": 2,
      "previous": 50
    },
    "expType": 1,
    "eventType": 1
  },
  {
    "id": 52,
    "type": 1,
    "specialty": 3,
    "sleepType": 1,
    "stats": {
      "frequency": 4400,
      "maxCarry": 9,
      "friendshipPoints": 5,
      "recruit": {
        "exp": 8,
        "shards": 17
      }
    },
    "berry": {
      "id": 1,
      "quantity": 1
    },
    "ingredientChain": 53,
    "skill": 3,
    "evolution": {
      "next": [
        {
          "id": 53,
          "conditions": [
            {
              "type": "candy",
              "count": 40
            },
            {
              "type": "level",
              "level": 21
            }
          ]
        }
      ],
      "stage": 1,
      "previous": null
    },
    "expType": 1,
    "eventType": 1
  },
  {
    "id": 53,
    "type": 1,
    "specialty": 3,
    "sleepType": 1,
    "stats": {
      "frequency": 3000,
      "maxCarry": 12,
      "friendshipPoints": 12,
      "recruit": {
        "exp": 116,
        "shards": 245
      }
    },
    "berry": {
      "id": 1,
      "quantity": 1
    },
    "ingredientChain": 53,
    "skill": 3,
    "evolution": {
      "next": [],
      "stage": 2,
      "previous": 52
    },
    "expType": 1,
    "eventType": 1
  },
  {
    "id": 54,
    "type": 3,
    "specialty": 3,
    "sleepType": 4,
    "stats": {
      "frequency": 5400,
      "maxCarry": 8,
      "friendshipPoints": 5,
      "recruit": {
        "exp": 9,
        "shards": 16
      }
    },
    "berry": {
      "id": 3,
      "quantity": 1
    },
    "ingredientChain": 55,
    "skill": 5,
    "evolution": {
      "next": [
        {
          "id": 55,
          "conditions": [
            {
              "type": "candy",
              "count": 40
            },
            {
              "type": "level",
              "level": 25
            }
          ]
        }
      ],
      "stage": 1,
      "previous": null
    },
    "expType": 1,
    "eventType": 1
  },
  {
    "id": 55,
    "type": 3,
    "specialty": 3,
    "sleepType": 0,
    "stats": {
      "frequency": 3400,
      "maxCarry": 11,
      "friendshipPoints": 12,
      "recruit": {
        "exp": 126,
        "shards": 227
      }
    },
    "berry": {
      "id": 3,
      "quantity": 1
    },
    "ingredientChain": 55,
    "skill": 5,
    "evolution": {
      "next": [],
      "stage": 2,
      "previous": 54
    },
    "expType": 1,
    "eventType": 1
  },
  {
    "id": 56,
    "type": 7,
    "specialty": 1,
    "sleepType": 4,
    "stats": {
      "frequency": 4200,
      "maxCarry": 12,
      "friendshipPoints": 5,
      "recruit": {
        "exp": 7,
        "shards": 19
      }
    },
    "berry": {
      "id": 7,
      "quantity": 2
    },
    "ingredientChain": 57,
    "skill": 5,
    "evolution": {
      "next": [
        {
          "id": 57,
          "conditions": [
            {
              "type": "candy",
              "count": 40
            },
            {
              "type": "level",
              "level": 21
            }
          ]
        }
      ],
      "stage": 1,
      "previous": null
    },
    "expType": 1,
    "eventType": 1
  },
  {
    "id": 57,
    "type": 7,
    "specialty": 1,
    "sleepType": 4,
    "stats": {
      "frequency": 2800,
      "maxCarry": 17,
      "friendshipPoints": 12,
      "recruit": {
        "exp": 116,
        "shards": 245
      }
    },
    "berry": {
      "id": 7,
      "quantity": 2
    },
    "ingredientChain": 57,
    "skill": 5,
    "evolution": {
      "next": [],
      "stage": 2,
      "previous": 56
    },
    "expType": 1,
    "eventType": 1
  },
  {
    "id": 58,
    "type": 2,
    "specialty": 3,
    "sleepType": 1,
    "stats": {
      "frequency": 4300,
      "maxCarry": 8,
      "friendshipPoints": 5,
      "recruit": {
        "exp": 9,
        "shards": 16
      }
    },
    "berry": {
      "id": 2,
      "quantity": 1
    },
    "ingredientChain": 59,
    "skill": 9,
    "evolution": {
      "next": [
        {
          "id": 59,
          "conditions": [
            {
              "type": "candy",
              "count": 80
            },
            {
              "type": "item",
              "item": 22,
              "count": 1
            }
          ]
        }
      ],
      "stage": 1,
      "previous": null
    },
    "expType": 1,
    "eventType": 1
  },
  {
    "id": 59,
    "type": 2,
    "specialty": 3,
    "sleepType": 1,
    "stats": {
      "frequency": 2500,
      "maxCarry": 16,
      "friendshipPoints": 20,
      "recruit": {
        "exp": 666,
        "shards": 1199
      }
    },
    "berry": {
      "id": 2,
      "quantity": 1
    },
    "ingredientChain": 59,
    "skill": 9,
    "evolution": {
      "next": [],
      "stage": 2,
      "previous": 58
    },
    "expType": 1,
    "eventType": 1
  },
  {
    "id": 69,
    "type": 5,
    "specialty": 2,
    "sleepType": 4,
    "stats": {
      "frequency": 5200,
      "maxCarry": 8,
      "friendshipPoints": 5,
      "recruit": {
        "exp": 9,
        "shards": 16
      }
    },
    "berry": {
      "id": 5,
      "quantity": 1
    },
    "ingredientChain": 71,
    "skill": 7,
    "evolution": {
      "next": [
        {
          "id": 70,
          "conditions": [
            {
              "type": "candy",
              "count": 40
            },
            {
              "type": "level",
              "level": 16
            }
          ]
        }
      ],
      "stage": 1,
      "previous": null
    },
    "expType": 1,
    "eventType": 1
  },
  {
    "id": 70,
    "type": 5,
    "specialty": 2,
    "sleepType": 4,
    "stats": {
      "frequency": 3800,
      "maxCarry": 12,
      "friendshipPoints": 12,
      "recruit": {
        "exp": 73,
        "shards": 131
      }
    },
    "berry": {
      "id": 5,
      "quantity": 1
    },
    "ingredientChain": 71,
    "skill": 7,
    "evolution": {
      "next": [
        {
          "id": 71,
          "conditions": [
            {
              "type": "candy",
              "count": 80
            },
            {
              "type": "item",
              "item": 25,
              "count": 1
            }
          ]
        }
      ],
      "stage": 2,
      "previous": 69
    },
    "expType": 1,
    "eventType": 1
  },
  {
    "id": 71,
    "type": 5,
    "specialty": 2,
    "sleepType": 4,
    "stats": {
      "frequency": 2800,
      "maxCarry": 17,
      "friendshipPoints": 20,
      "recruit": {
        "exp": 397,
        "shards": 715
      }
    },
    "berry": {
      "id": 5,
      "quantity": 1
    },
    "ingredientChain": 71,
    "skill": 7,
    "evolution": {
      "next": [],
      "stage": 3,
      "previous": 70
    },
    "expType": 1,
    "eventType": 1
  },
  {
    "id": 74,
    "type": 13,
    "specialty": 2,
    "sleepType": 0,
    "stats": {
      "frequency": 5700,
      "maxCarry": 9,
      "friendshipPoints": 5,
      "recruit": {
        "exp": 7,
        "shards": 19
      }
    },
    "berry": {
      "id": 13,
      "quantity": 1
    },
    "ingredientChain": 76,
    "skill": 5,
    "evolution": {
      "next": [
        {
          "id": 75,
          "conditions": [
            {
              "type": "candy",
              "count": 40
            },
            {
              "type": "level",
              "level": 19
            }
          ]
        }
      ],
      "stage": 1,
      "previous": null
    },
    "expType": 1,
    "eventType": 1
  },
  {
    "id": 75,
    "type": 13,
    "specialty": 2,
    "sleepType": 0,
    "stats": {
      "frequency": 4000,
      "maxCarry": 12,
      "friendshipPoints": 12,
      "recruit": {
        "exp": 67,
        "shards": 141
      }
    },
    "berry": {
      "id": 13,
      "quantity": 1
    },
    "ingredientChain": 76,
    "skill": 5,
    "evolution": {
      "next": [
        {
          "id": 76,
          "conditions": [
            {
              "type": "candy",
              "count": 80
            },
            {
              "type": "item",
              "item": 21,
              "count": 1
            }
          ]
        }
      ],
      "stage": 2,
      "previous": 74
    },
    "expType": 1,
    "eventType": 1
  },
  {
    "id": 76,
    "type": 13,
    "specialty": 2,
    "sleepType": 0,
    "stats": {
      "frequency": 3100,
      "maxCarry": 16,
      "friendshipPoints": 22,
      "recruit": {
        "exp": 574,
        "shards": 1033
      }
    },
    "berry": {
      "id": 13,
      "quantity": 1
    },
    "ingredientChain": 76,
    "skill": 5,
    "evolution": {
      "next": [],
      "stage": 3,
      "previous": 75
    },
    "expType": 1,
    "eventType": 1
  },
  {
    "id": 79,
    "type": 3,
    "specialty": 3,
    "sleepType": 1,
    "stats": {
      "frequency": 5700,
      "maxCarry": 9,
      "friendshipPoints": 5,
      "recruit": {
        "exp": 11,
        "shards": 12
      }
    },
    "berry": {
      "id": 3,
      "quantity": 1
    },
    "ingredientChain": 80,
    "skill": 4,
    "evolution": {
      "next": [
        {
          "id": 80,
          "conditions": [
            {
              "type": "candy",
              "count": 40
            },
            {
              "type": "level",
              "level": 28
            }
          ]
        },
        {
          "id": 199,
          "conditions": [
            {
              "type": "candy",
              "count": 80
            },
            {
              "type": "item",
              "item": 31,
              "count": 1
            },
            {
              "type": "item",
              "item": 21,
              "count": 1
            }
          ]
        }
      ],
      "stage": 1,
      "previous": null
    },
    "expType": 1,
    "eventType": 1
  },
  {
    "id": 80,
    "type": 3,
    "specialty": 3,
    "sleepType": 1,
    "stats": {
      "frequency": 3800,
      "maxCarry": 10,
      "friendshipPoints": 12,
      "recruit": {
        "exp": 136,
        "shards": 209
      }
    },
    "berry": {
      "id": 3,
      "quantity": 1
    },
    "ingredientChain": 80,
    "skill": 4,
    "evolution": {
      "next": [],
      "stage": 2,
      "previous": 79
    },
    "expType": 1,
    "eventType": 1
  },
  {
    "id": 81,
    "type": 17,
    "specialty": 3,
    "sleepType": 0,
    "stats": {
      "frequency": 5800,
      "maxCarry": 8,
      "friendshipPoints": 5,
      "recruit": {
        "exp": 7,
        "shards": 20
      }
    },
    "berry": {
      "id": 17,
      "quantity": 1
    },
    "ingredientChain": 462,
    "skill": 11,
    "evolution": {
      "next": [
        {
          "id": 82,
          "conditions": [
            {
              "type": "candy",
              "count": 40
            },
            {
              "type": "level",
              "level": 23
            }
          ]
        }
      ],
      "stage": 1,
      "previous": null
    },
    "expType": 1,
    "eventType": 1
  },
  {
    "id": 82,
    "type": 17,
    "specialty": 3,
    "sleepType": 0,
    "stats": {
      "frequency": 4000,
      "maxCarry": 11,
      "friendshipPoints": 12,
      "recruit": {
        "exp": 95,
        "shards": 284
      }
    },
    "berry": {
      "id": 17,
      "quantity": 1
    },
    "ingredientChain": 462,
    "skill": 11,
    "evolution": {
      "next": [
        {
          "id": 462,
          "conditions": [
            {
              "type": "candy",
              "count": 80
            },
            {
              "type": "item",
              "item": 24,
              "count": 1
            }
          ]
        }
      ],
      "stage": 2,
      "previous": 81
    },
    "expType": 1,
    "eventType": 1
  },
  {
    "id": 84,
    "type": 10,
    "specialty": 1,
    "sleepType": 0,
    "stats": {
      "frequency": 3800,
      "maxCarry": 13,
      "friendshipPoints": 5,
      "recruit": {
        "exp": 7,
        "shards": 20
      }
    },
    "berry": {
      "id": 10,
      "quantity": 2
    },
    "ingredientChain": 85,
    "skill": 7,
    "evolution": {
      "next": [
        {
          "id": 85,
          "conditions": [
            {
              "type": "candy",
              "count": 40
            },
            {
              "type": "level",
              "level": 23
            }
          ]
        }
      ],
      "stage": 1,
      "previous": null
    },
    "expType": 1,
    "eventType": 1
  },
  {
    "id": 85,
    "type": 10,
    "specialty": 1,
    "sleepType": 0,
    "stats": {
      "frequency": 2400,
      "maxCarry": 21,
      "friendshipPoints": 12,
      "recruit": {
        "exp": 60,
        "shards": 155
      }
    },
    "berry": {
      "id": 10,
      "quantity": 2
    },
    "ingredientChain": 85,
    "skill": 7,
    "evolution": {
      "next": [],
      "stage": 2,
      "previous": 84
    },
    "expType": 1,
    "eventType": 1
  },
  {
    "id": 92,
    "type": 14,
    "specialty": 2,
    "sleepType": 4,
    "stats": {
      "frequency": 3800,
      "maxCarry": 10,
      "friendshipPoints": 5,
      "recruit": {
        "exp": 7,
        "shards": 20
      }
    },
    "berry": {
      "id": 14,
      "quantity": 1
    },
    "ingredientChain": 94,
    "skill": 5,
    "evolution": {
      "next": [
        {
          "id": 93,
          "conditions": [
            {
              "type": "candy",
              "count": 40
            },
            {
              "type": "level",
              "level": 19
            }
          ]
        }
      ],
      "stage": 1,
      "previous": null
    },
    "expType": 1,
    "eventType": 1
  },
  {
    "id": 93,
    "type": 14,
    "specialty": 2,
    "sleepType": 4,
    "stats": {
      "frequency": 3000,
      "maxCarry": 14,
      "friendshipPoints": 12,
      "recruit": {
        "exp": 62,
        "shards": 186
      }
    },
    "berry": {
      "id": 14,
      "quantity": 1
    },
    "ingredientChain": 94,
    "skill": 5,
    "evolution": {
      "next": [
        {
          "id": 94,
          "conditions": [
            {
              "type": "candy",
              "count": 80
            },
            {
              "type": "item",
              "item": 21,
              "count": 1
            }
          ]
        }
      ],
      "stage": 2,
      "previous": 92
    },
    "expType": 1,
    "eventType": 1
  },
  {
    "id": 94,
    "type": 14,
    "specialty": 2,
    "sleepType": 4,
    "stats": {
      "frequency": 2200,
      "maxCarry": 18,
      "friendshipPoints": 22,
      "recruit": {
        "exp": 431,
        "shards": 1291
      }
    },
    "berry": {
      "id": 14,
      "quantity": 1
    },
    "ingredientChain": 94,
    "skill": 5,
    "evolution": {
      "next": [],
      "stage": 3,
      "previous": 93
    },
    "expType": 1,
    "eventType": 1
  },
  {
    "id": 95,
    "type": 13,
    "specialty": 1,
    "sleepType": 0,
    "stats": {
      "frequency": 3100,
      "maxCarry": 22,
      "friendshipPoints": 16,
      "recruit": {
        "exp": 250,
        "shards": 749
      }
    },
    "berry": {
      "id": 13,
      "quantity": 2
    },
    "ingredientChain": 95,
    "skill": 10,
    "evolution": {
      "next": [
        {
          "id": 208,
          "conditions": [
            {
              "type": "candy",
              "count": 80
            },
            {
              "type": "item",
              "item": 29,
              "count": 1
            },
            {
              "type": "item",
              "item": 21,
              "count": 1
            }
          ]
        }
      ],
      "stage": 1,
      "previous": null
    },
    "expType": 1,
    "eventType": 1
  },
  {
    "id": 104,
    "type": 9,
    "specialty": 1,
    "sleepType": 0,
    "stats": {
      "frequency": 4800,
      "maxCarry": 10,
      "friendshipPoints": 5,
      "recruit": {
        "exp": 9,
        "shards": 16
      }
    },
    "berry": {
      "id": 9,
      "quantity": 2
    },
    "ingredientChain": 105,
    "skill": 7,
    "evolution": {
      "next": [
        {
          "id": 105,
          "conditions": [
            {
              "type": "candy",
              "count": 40
            },
            {
              "type": "level",
              "level": 21
            }
          ]
        }
      ],
      "stage": 1,
      "previous": null
    },
    "expType": 1,
    "eventType": 1
  },
  {
    "id": 105,
    "type": 9,
    "specialty": 1,
    "sleepType": 0,
    "stats": {
      "frequency": 3500,
      "maxCarry": 15,
      "friendshipPoints": 12,
      "recruit": {
        "exp": 93,
        "shards": 197
      }
    },
    "berry": {
      "id": 9,
      "quantity": 2
    },
    "ingredientChain": 105,
    "skill": 7,
    "evolution": {
      "next": [],
      "stage": 2,
      "previous": 104
    },
    "expType": 1,
    "eventType": 1
  },
  {
    "id": 115,
    "type": 1,
    "specialty": 2,
    "sleepType": 1,
    "stats": {
      "frequency": 2800,
      "maxCarry": 16,
      "friendshipPoints": 16,
      "recruit": {
        "exp": 416,
        "shards": 449
      }
    },
    "berry": {
      "id": 1,
      "quantity": 1
    },
    "ingredientChain": 115,
    "skill": 10,
    "evolution": {
      "next": [],
      "stage": 1,
      "previous": null
    },
    "expType": 1,
    "eventType": 1
  },
  {
    "id": 122,
    "type": 11,
    "specialty": 2,
    "sleepType": 1,
    "stats": {
      "frequency": 2800,
      "maxCarry": 17,
      "friendshipPoints": 12,
      "recruit": {
        "exp": 95,
        "shards": 284
      }
    },
    "berry": {
      "id": 11,
      "quantity": 1
    },
    "ingredientChain": 439,
    "skill": 1,
    "evolution": {
      "next": [],
      "stage": 2,
      "previous": 439
    },
    "expType": 1,
    "eventType": 1
  },
  {
    "id": 127,
    "type": 12,
    "specialty": 2,
    "sleepType": 4,
    "stats": {
      "frequency": 2400,
      "maxCarry": 19,
      "friendshipPoints": 16,
      "recruit": {
        "exp": 235,
        "shards": 608
      }
    },
    "berry": {
      "id": 12,
      "quantity": 1
    },
    "ingredientChain": 127,
    "skill": 1,
    "evolution": {
      "next": [],
      "stage": 1,
      "previous": null
    },
    "expType": 1,
    "eventType": 1
  },
  {
    "id": 132,
    "type": 1,
    "specialty": 2,
    "sleepType": 1,
    "stats": {
      "frequency": 3500,
      "maxCarry": 13,
      "friendshipPoints": 16,
      "recruit": {
        "exp": 219,
        "shards": 394
      }
    },
    "berry": {
      "id": 1,
      "quantity": 1
    },
    "ingredientChain": 132,
    "skill": 5,
    "evolution": {
      "next": [],
      "stage": 1,
      "previous": null
    },
    "expType": 1,
    "eventType": 1
  },
  {
    "id": 133,
    "type": 1,
    "specialty": 3,
    "sleepType": 1,
    "stats": {
      "frequency": 3700,
      "maxCarry": 12,
      "friendshipPoints": 5,
      "recruit": {
        "exp": 20,
        "shards": 36
      }
    },
    "berry": {
      "id": 1,
      "quantity": 1
    },
    "ingredientChain": 133,
    "skill": 10,
    "evolution": {
      "next": [
        {
          "id": 134,
          "conditions": [
            {
              "type": "candy",
              "count": 80
            },
            {
              "type": "item",
              "item": 23,
              "count": 1
            }
          ]
        },
        {
          "id": 135,
          "conditions": [
            {
              "type": "candy",
              "count": 80
            },
            {
              "type": "item",
              "item": 24,
              "count": 1
            }
          ]
        },
        {
          "id": 136,
          "conditions": [
            {
              "type": "candy",
              "count": 80
            },
            {
              "type": "item",
              "item": 22,
              "count": 1
            }
          ]
        },
        {
          "id": 197,
          "conditions": [
            {
              "type": "candy",
              "count": 80
            },
            {
              "type": "sleepTime",
              "hours": 150.0
            },
            {
              "type": "timing",
              "startHour": 18,
              "endHour": 6
            }
          ]
        },
        {
          "id": 196,
          "conditions": [
            {
              "type": "candy",
              "count": 80
            },
            {
              "type": "sleepTime",
              "hours": 150.0
            },
            {
              "type": "timing",
              "startHour": 6,
              "endHour": 18
            }
          ]
        },
        {
          "id": 470,
          "conditions": [
            {
              "type": "candy",
              "count": 80
            },
            {
              "type": "item",
              "item": 25,
              "count": 1
            }
          ]
        },
        {
          "id": 471,
          "conditions": [
            {
              "type": "candy",
              "count": 80
            },
            {
              "type": "item",
              "item": 26,
              "count": 1
            }
          ]
        },
        {
          "id": 700,
          "conditions": [
            {
              "type": "candy",
              "count": 80
            },
            {
              "type": "sleepTime",
              "hours": 150.0
            }
          ]
        }
      ],
      "stage": 1,
      "previous": null
    },
    "expType": 1,
    "eventType": 1
  },
  {
    "id": 134,
    "type": 3,
    "specialty": 3,
    "sleepType": 0,
    "stats": {
      "frequency": 3100,
      "maxCarry": 13,
      "friendshipPoints": 20,
      "recruit": {
        "exp": 675,
        "shards": 729
      }
    },
    "berry": {
      "id": 3,
      "quantity": 1
    },
    "ingredientChain": 134,
    "skill": 10,
    "evolution": {
      "next": [],
      "stage": 2,
      "previous": 133
    },
    "expType": 1,
    "eventType": 1
  },
  {
    "id": 135,
    "type": 4,
    "specialty": 3,
    "sleepType": 1,
    "stats": {
      "frequency": 2200,
      "maxCarry": 17,
      "friendshipPoints": 20,
      "recruit": {
        "exp": 443,
        "shards": 1147
      }
    },
    "berry": {
      "id": 4,
      "quantity": 1
    },
    "ingredientChain": 135,
    "skill": 9,
    "evolution": {
      "next": [],
      "stage": 2,
      "previous": 133
    },
    "expType": 1,
    "eventType": 1
  },
  {
    "id": 136,
    "type": 2,
    "specialty": 3,
    "sleepType": 1,
    "stats": {
      "frequency": 2700,
      "maxCarry": 14,
      "friendshipPoints": 20,
      "recruit": {
        "exp": 443,
        "shards": 1147
      }
    },
    "berry": {
      "id": 2,
      "quantity": 1
    },
    "ingredientChain": 136,
    "skill": 11,
    "evolution": {
      "next": [],
      "stage": 2,
      "previous": 133
    },
    "expType": 1,
    "eventType": 1
  },
  {
    "id": 152,
    "type": 5,
    "specialty": 1,
    "sleepType": 4,
    "stats": {
      "frequency": 4400,
      "maxCarry": 12,
      "friendshipPoints": 5,
      "recruit": {
        "exp": 18,
        "shards": 39
      }
    },
    "berry": {
      "id": 5,
      "quantity": 2
    },
    "ingredientChain": 154,
    "skill": 5,
    "evolution": {
      "next": [
        {
          "id": 153,
          "conditions": [
            {
              "type": "candy",
              "count": 40
            },
            {
              "type": "level",
              "level": 12
            }
          ]
        }
      ],
      "stage": 1,
      "previous": null
    },
    "expType": 1,
    "eventType": 1
  },
  {
    "id": 153,
    "type": 5,
    "specialty": 1,
    "sleepType": 4,
    "stats": {
      "frequency": 3300,
      "maxCarry": 17,
      "friendshipPoints": 12,
      "recruit": {
        "exp": 116,
        "shards": 245
      }
    },
    "berry": {
      "id": 5,
      "quantity": 2
    },
    "ingredientChain": 154,
    "skill": 5,
    "evolution": {
      "next": [
        {
          "id": 154,
          "conditions": [
            {
              "type": "candy",
              "count": 80
            },
            {
              "type": "level",
              "level": 24
            }
          ]
        }
      ],
      "stage": 2,
      "previous": 152
    },
    "expType": 1,
    "eventType": 1
  },
  {
    "id": 154,
    "type": 5,
    "specialty": 1,
    "sleepType": 4,
    "stats": {
      "frequency": 2800,
      "maxCarry": 20,
      "friendshipPoints": 20,
      "recruit": {
        "exp": 574,
        "shards": 1033
      }
    },
    "berry": {
      "id": 5,
      "quantity": 2
    },
    "ingredientChain": 154,
    "skill": 5,
    "evolution": {
      "next": [],
      "stage": 3,
      "previous": 153
    },
    "expType": 1,
    "eventType": 1
  },
  {
    "id": 155,
    "type": 2,
    "specialty": 1,
    "sleepType": 1,
    "stats": {
      "frequency": 3500,
      "maxCarry": 14,
      "friendshipPoints": 5,
      "recruit": {
        "exp": 16,
        "shards": 42
      }
    },
    "berry": {
      "id": 2,
      "quantity": 2
    },
    "ingredientChain": 157,
    "skill": 5,
    "evolution": {
      "next": [
        {
          "id": 156,
          "conditions": [
            {
              "type": "candy",
              "count": 40
            },
            {
              "type": "level",
              "level": 11
            }
          ]
        }
      ],
      "stage": 1,
      "previous": null
    },
    "expType": 1,
    "eventType": 1
  },
  {
    "id": 156,
    "type": 2,
    "specialty": 1,
    "sleepType": 1,
    "stats": {
      "frequency": 3000,
      "maxCarry": 18,
      "friendshipPoints": 12,
      "recruit": {
        "exp": 116,
        "shards": 245
      }
    },
    "berry": {
      "id": 2,
      "quantity": 2
    },
    "ingredientChain": 157,
    "skill": 5,
    "evolution": {
      "next": [
        {
          "id": 157,
          "conditions": [
            {
              "type": "candy",
              "count": 80
            },
            {
              "type": "level",
              "level": 27
            }
          ]
        }
      ],
      "stage": 2,
      "previous": 155
    },
    "expType": 1,
    "eventType": 1
  },
  {
    "id": 157,
    "type": 2,
    "specialty": 1,
    "sleepType": 1,
    "stats": {
      "frequency": 2400,
      "maxCarry": 23,
      "friendshipPoints": 20,
      "recruit": {
        "exp": 528,
        "shards": 1116
      }
    },
    "berry": {
      "id": 2,
      "quantity": 2
    },
    "ingredientChain": 157,
    "skill": 5,
    "evolution": {
      "next": [],
      "stage": 3,
      "previous": 156
    },
    "expType": 1,
    "eventType": 1
  },
  {
    "id": 158,
    "type": 3,
    "specialty": 1,
    "sleepType": 0,
    "stats": {
      "frequency": 4500,
      "maxCarry": 11,
      "friendshipPoints": 5,
      "recruit": {
        "exp": 20,
        "shards": 36
      }
    },
    "berry": {
      "id": 3,
      "quantity": 2
    },
    "ingredientChain": 160,
    "skill": 5,
    "evolution": {
      "next": [
        {
          "id": 159,
          "conditions": [
            {
              "type": "candy",
              "count": 40
            },
            {
              "type": "level",
              "level": 14
            }
          ]
        }
      ],
      "stage": 1,
      "previous": null
    },
    "expType": 1,
    "eventType": 1
  },
  {
    "id": 159,
    "type": 3,
    "specialty": 1,
    "sleepType": 0,
    "stats": {
      "frequency": 3400,
      "maxCarry": 15,
      "friendshipPoints": 12,
      "recruit": {
        "exp": 126,
        "shards": 227
      }
    },
    "berry": {
      "id": 3,
      "quantity": 2
    },
    "ingredientChain": 160,
    "skill": 5,
    "evolution": {
      "next": [
        {
          "id": 160,
          "conditions": [
            {
              "type": "candy",
              "count": 80
            },
            {
              "type": "level",
              "level": 23
            }
          ]
        }
      ],
      "stage": 2,
      "previous": 158
    },
    "expType": 1,
    "eventType": 1
  },
  {
    "id": 160,
    "type": 3,
    "specialty": 1,
    "sleepType": 0,
    "stats": {
      "frequency": 2800,
      "maxCarry": 19,
      "friendshipPoints": 20,
      "recruit": {
        "exp": 574,
        "shards": 1033
      }
    },
    "berry": {
      "id": 3,
      "quantity": 2
    },
    "ingredientChain": 160,
    "skill": 5,
    "evolution": {
      "next": [],
      "stage": 3,
      "previous": 159
    },
    "expType": 1,
    "eventType": 1
  },
  {
    "id": 172,
    "type": 4,
    "specialty": 1,
    "sleepType": 0,
    "stats": {
      "frequency": 4300,
      "maxCarry": 10,
      "friendshipPoints": 5,
      "recruit": {
        "exp": 7,
        "shards": 20
      }
    },
    "berry": {
      "id": 4,
      "quantity": 2
    },
    "ingredientChain": 26,
    "skill": 1,
    "evolution": {
      "next": [
        {
          "id": 25,
          "conditions": [
            {
              "type": "candy",
              "count": 20
            },
            {
              "type": "sleepTime",
              "hours": 50.0
            }
          ]
        }
      ],
      "stage": 1,
      "previous": null
    },
    "expType": 1,
    "eventType": 1
  },
  {
    "id": 173,
    "type": 18,
    "specialty": 1,
    "sleepType": 0,
    "stats": {
      "frequency": 5600,
      "maxCarry": 10,
      "friendshipPoints": 5,
      "recruit": {
        "exp": 25,
        "shards": 27
      }
    },
    "berry": {
      "id": 18,
      "quantity": 2
    },
    "ingredientChain": 173,
    "skill": 13,
    "evolution": {
      "next": [
        {
          "id": 35,
          "conditions": [
            {
              "type": "candy",
              "count": 20
            },
            {
              "type": "sleepTime",
              "hours": 50.0
            }
          ]
        }
      ],
      "stage": 1,
      "previous": null
    },
    "expType": 1,
    "eventType": 1
  },
  {
    "id": 174,
    "type": 18,
    "specialty": 3,
    "sleepType": 0,
    "stats": {
      "frequency": 5200,
      "maxCarry": 8,
      "friendshipPoints": 5,
      "recruit": {
        "exp": 11,
        "shards": 12
      }
    },
    "berry": {
      "id": 18,
      "quantity": 1
    },
    "ingredientChain": 40,
    "skill": 8,
    "evolution": {
      "next": [
        {
          "id": 39,
          "conditions": [
            {
              "type": "candy",
              "count": 20
            },
            {
              "type": "sleepTime",
              "hours": 50.0
            }
          ]
        }
      ],
      "stage": 1,
      "previous": null
    },
    "expType": 1,
    "eventType": 1
  },
  {
    "id": 175,
    "type": 18,
    "specialty": 3,
    "sleepType": 0,
    "stats": {
      "frequency": 4800,
      "maxCarry": 8,
      "friendshipPoints": 5,
      "recruit": {
        "exp": 18,
        "shards": 39
      }
    },
    "berry": {
      "id": 18,
      "quantity": 1
    },
    "ingredientChain": 468,
    "skill": 13,
    "evolution": {
      "next": [
        {
          "id": 176,
          "conditions": [
            {
              "type": "candy",
              "count": 20
            },
            {
              "type": "sleepTime",
              "hours": 50.0
            }
          ]
        }
      ],
      "stage": 1,
      "previous": null
    },
    "expType": 1,
    "eventType": 1
  },
  {
    "id": 176,
    "type": 18,
    "specialty": 3,
    "sleepType": 1,
    "stats": {
      "frequency": 3800,
      "maxCarry": 10,
      "friendshipPoints": 12,
      "recruit": {
        "exp": 76,
        "shards": 161
      }
    },
    "berry": {
      "id": 18,
      "quantity": 1
    },
    "ingredientChain": 468,
    "skill": 13,
    "evolution": {
      "next": [
        {
          "id": 468,
          "conditions": [
            {
              "type": "candy",
              "count": 80
            },
            {
              "type": "item",
              "item": 28,
              "count": 1
            }
          ]
        }
      ],
      "stage": 2,
      "previous": 175
    },
    "expType": 1,
    "eventType": 1
  },
  {
    "id": 179,
    "type": 4,
    "specialty": 3,
    "sleepType": 1,
    "stats": {
      "frequency": 4600,
      "maxCarry": 9,
      "friendshipPoints": 5,
      "recruit": {
        "exp": 11,
        "shards": 13
      }
    },
    "berry": {
      "id": 4,
      "quantity": 1
    },
    "ingredientChain": 181,
    "skill": 2,
    "evolution": {
      "next": [
        {
          "id": 180,
          "conditions": [
            {
              "type": "candy",
              "count": 40
            },
            {
              "type": "level",
              "level": 11
            }
          ]
        }
      ],
      "stage": 1,
      "previous": null
    },
    "expType": 1,
    "eventType": 1
  },
  {
    "id": 180,
    "type": 4,
    "specialty": 3,
    "sleepType": 1,
    "stats": {
      "frequency": 3300,
      "maxCarry": 11,
      "friendshipPoints": 12,
      "recruit": {
        "exp": 79,
        "shards": 121
      }
    },
    "berry": {
      "id": 4,
      "quantity": 1
    },
    "ingredientChain": 181,
    "skill": 2,
    "evolution": {
      "next": [
        {
          "id": 181,
          "conditions": [
            {
              "type": "candy",
              "count": 80
            },
            {
              "type": "level",
              "level": 23
            }
          ]
        }
      ],
      "stage": 2,
      "previous": 179
    },
    "expType": 1,
    "eventType": 1
  },
  {
    "id": 181,
    "type": 4,
    "specialty": 3,
    "sleepType": 1,
    "stats": {
      "frequency": 2500,
      "maxCarry": 15,
      "friendshipPoints": 20,
      "recruit": {
        "exp": 397,
        "shards": 715
      }
    },
    "berry": {
      "id": 4,
      "quantity": 1
    },
    "ingredientChain": 181,
    "skill": 2,
    "evolution": {
      "next": [],
      "stage": 3,
      "previous": 180
    },
    "expType": 1,
    "eventType": 1
  },
  {
    "id": 185,
    "type": 13,
    "specialty": 3,
    "sleepType": 0,
    "stats": {
      "frequency": 4000,
      "maxCarry": 10,
      "friendshipPoints": 7,
      "recruit": {
        "exp": 23,
        "shards": 41
      }
    },
    "berry": {
      "id": 13,
      "quantity": 1
    },
    "ingredientChain": 185,
    "skill": 2,
    "evolution": {
      "next": [],
      "stage": 2,
      "previous": 438
    },
    "expType": 1,
    "eventType": 1
  },
  {
    "id": 196,
    "type": 11,
    "specialty": 3,
    "sleepType": 1,
    "stats": {
      "frequency": 2400,
      "maxCarry": 16,
      "friendshipPoints": 20,
      "recruit": {
        "exp": 443,
        "shards": 1147
      }
    },
    "berry": {
      "id": 11,
      "quantity": 1
    },
    "ingredientChain": 196,
    "skill": 2,
    "evolution": {
      "next": [],
      "stage": 2,
      "previous": 133
    },
    "expType": 1,
    "eventType": 1
  },
  {
    "id": 197,
    "type": 16,
    "specialty": 3,
    "sleepType": 4,
    "stats": {
      "frequency": 3200,
      "maxCarry": 14,
      "friendshipPoints": 20,
      "recruit": {
        "exp": 583,
        "shards": 894
      }
    },
    "berry": {
      "id": 16,
      "quantity": 1
    },
    "ingredientChain": 197,
    "skill": 7,
    "evolution": {
      "next": [],
      "stage": 2,
      "previous": 133
    },
    "expType": 1,
    "eventType": 1
  },
  {
    "id": 199,
    "type": 3,
    "specialty": 3,
    "sleepType": 1,
    "stats": {
      "frequency": 3400,
      "maxCarry": 11,
      "friendshipPoints": 20,
      "recruit": {
        "exp": 719,
        "shards": 1103
      }
    },
    "berry": {
      "id": 3,
      "quantity": 1
    },
    "ingredientChain": 199,
    "skill": 4,
    "evolution": {
      "next": [],
      "stage": 2,
      "previous": 79
    },
    "expType": 1,
    "eventType": 1
  },
  {
    "id": 202,
    "type": 11,
    "specialty": 3,
    "sleepType": 1,
    "stats": {
      "frequency": 3500,
      "maxCarry": 10,
      "friendshipPoints": 7,
      "recruit": {
        "exp": 29,
        "shards": 31
      }
    },
    "berry": {
      "id": 11,
      "quantity": 1
    },
    "ingredientChain": 202,
    "skill": 4,
    "evolution": {
      "next": [],
      "stage": 2,
      "previous": 360
    },
    "expType": 1,
    "eventType": 1
  },
  {
    "id": 208,
    "type": 17,
    "specialty": 1,
    "sleepType": 0,
    "stats": {
      "frequency": 3000,
      "maxCarry": 25,
      "friendshipPoints": 20,
      "recruit": {
        "exp": 1170,
        "shards": 2473
      }
    },
    "berry": {
      "id": 17,
      "quantity": 2
    },
    "ingredientChain": 95,
    "skill": 10,
    "evolution": {
      "next": [],
      "stage": 2,
      "previous": 95
    },
    "expType": 1,
    "eventType": 1
  },
  {
    "id": 214,
    "type": 12,
    "specialty": 3,
    "sleepType": 4,
    "stats": {
      "frequency": 2500,
      "maxCarry": 15,
      "friendshipPoints": 16,
      "recruit": {
        "exp": 286,
        "shards": 515
      }
    },
    "berry": {
      "id": 12,
      "quantity": 1
    },
    "ingredientChain": 214,
    "skill": 10,
    "evolution": {
      "next": [],
      "stage": 1,
      "previous": null
    },
    "expType": 1,
    "eventType": 1
  },
  {
    "id": 228,
    "type": 16,
    "specialty": 1,
    "sleepType": 4,
    "stats": {
      "frequency": 4900,
      "maxCarry": 10,
      "friendshipPoints": 5,
      "recruit": {
        "exp": 8,
        "shards": 17
      }
    },
    "berry": {
      "id": 16,
      "quantity": 2
    },
    "ingredientChain": 229,
    "skill": 1,
    "evolution": {
      "next": [
        {
          "id": 229,
          "conditions": [
            {
              "type": "candy",
              "count": 40
            },
            {
              "type": "level",
              "level": 18
            }
          ]
        }
      ],
      "stage": 1,
      "previous": null
    },
    "expType": 1,
    "eventType": 1
  },
  {
    "id": 229,
    "type": 16,
    "specialty": 1,
    "sleepType": 4,
    "stats": {
      "frequency": 3300,
      "maxCarry": 16,
      "friendshipPoints": 12,
      "recruit": {
        "exp": 144,
        "shards": 303
      }
    },
    "berry": {
      "id": 16,
      "quantity": 2
    },
    "ingredientChain": 229,
    "skill": 1,
    "evolution": {
      "next": [],
      "stage": 2,
      "previous": 228
    },
    "expType": 1,
    "eventType": 1
  },
  {
    "id": 246,
    "type": 13,
    "specialty": 2,
    "sleepType": 0,
    "stats": {
      "frequency": 4800,
      "maxCarry": 9,
      "friendshipPoints": 5,
      "recruit": {
        "exp": 30,
        "shards": 54
      }
    },
    "berry": {
      "id": 13,
      "quantity": 1
    },
    "ingredientChain": 248,
    "skill": 7,
    "evolution": {
      "next": [
        {
          "id": 247,
          "conditions": [
            {
              "type": "candy",
              "count": 40
            },
            {
              "type": "level",
              "level": 23
            }
          ]
        }
      ],
      "stage": 1,
      "previous": null
    },
    "expType": 2,
    "eventType": 1
  },
  {
    "id": 247,
    "type": 13,
    "specialty": 2,
    "sleepType": 0,
    "stats": {
      "frequency": 3600,
      "maxCarry": 13,
      "friendshipPoints": 12,
      "recruit": {
        "exp": 156,
        "shards": 281
      }
    },
    "berry": {
      "id": 13,
      "quantity": 1
    },
    "ingredientChain": 248,
    "skill": 7,
    "evolution": {
      "next": [
        {
          "id": 248,
          "conditions": [
            {
              "type": "candy",
              "count": 100
            },
            {
              "type": "level",
              "level": 41
            }
          ]
        }
      ],
      "stage": 2,
      "previous": 246
    },
    "expType": 2,
    "eventType": 1
  },
  {
    "id": 248,
    "type": 16,
    "specialty": 2,
    "sleepType": 4,
    "stats": {
      "frequency": 2700,
      "maxCarry": 19,
      "friendshipPoints": 25,
      "recruit": {
        "exp": 1432,
        "shards": 2578
      }
    },
    "berry": {
      "id": 16,
      "quantity": 1
    },
    "ingredientChain": 248,
    "skill": 7,
    "evolution": {
      "next": [],
      "stage": 3,
      "previous": 247
    },
    "expType": 2,
    "eventType": 1
  },
  {
    "id": 287,
    "type": 1,
    "specialty": 1,
    "sleepType": 1,
    "stats": {
      "frequency": 4900,
      "maxCarry": 7,
      "friendshipPoints": 5,
      "recruit": {
        "exp": 11,
        "shards": 12
      }
    },
    "berry": {
      "id": 1,
      "quantity": 2
    },
    "ingredientChain": 289,
    "skill": 10,
    "evolution": {
      "next": [
        {
          "id": 288,
          "conditions": [
            {
              "type": "candy",
              "count": 40
            },
            {
              "type": "level",
              "level": 14
            }
          ]
        }
      ],
      "stage": 1,
      "previous": null
    },
    "expType": 1,
    "eventType": 1
  },
  {
    "id": 288,
    "type": 1,
    "specialty": 1,
    "sleepType": 4,
    "stats": {
      "frequency": 3200,
      "maxCarry": 9,
      "friendshipPoints": 12,
      "recruit": {
        "exp": 122,
        "shards": 187
      }
    },
    "berry": {
      "id": 1,
      "quantity": 2
    },
    "ingredientChain": 289,
    "skill": 10,
    "evolution": {
      "next": [
        {
          "id": 289,
          "conditions": [
            {
              "type": "candy",
              "count": 80
            },
            {
              "type": "level",
              "level": 27
            }
          ]
        }
      ],
      "stage": 2,
      "previous": 287
    },
    "expType": 1,
    "eventType": 1
  },
  {
    "id": 289,
    "type": 1,
    "specialty": 1,
    "sleepType": 1,
    "stats": {
      "frequency": 3800,
      "maxCarry": 12,
      "friendshipPoints": 22,
      "recruit": {
        "exp": 1108,
        "shards": 1196
      }
    },
    "berry": {
      "id": 1,
      "quantity": 2
    },
    "ingredientChain": 289,
    "skill": 10,
    "evolution": {
      "next": [],
      "stage": 3,
      "previous": 288
    },
    "expType": 1,
    "eventType": 1
  },
  {
    "id": 302,
    "type": 16,
    "specialty": 3,
    "sleepType": 4,
    "stats": {
      "frequency": 3600,
      "maxCarry": 10,
      "friendshipPoints": 16,
      "recruit": {
        "exp": 180,
        "shards": 465
      }
    },
    "berry": {
      "id": 16,
      "quantity": 1
    },
    "ingredientChain": 302,
    "skill": 6,
    "evolution": {
      "next": [],
      "stage": 1,
      "previous": null
    },
    "expType": 1,
    "eventType": 1
  },
  {
    "id": 316,
    "type": 8,
    "specialty": 3,
    "sleepType": 4,
    "stats": {
      "frequency": 5900,
      "maxCarry": 8,
      "friendshipPoints": 5,
      "recruit": {
        "exp": 11,
        "shards": 12
      }
    },
    "berry": {
      "id": 8,
      "quantity": 1
    },
    "ingredientChain": 317,
    "skill": 6,
    "evolution": {
      "next": [
        {
          "id": 317,
          "conditions": [
            {
              "type": "candy",
              "count": 40
            },
            {
              "type": "level",
              "level": 20
            }
          ]
        }
      ],
      "stage": 1,
      "previous": null
    },
    "expType": 1,
    "eventType": 1
  },
  {
    "id": 317,
    "type": 8,
    "specialty": 3,
    "sleepType": 4,
    "stats": {
      "frequency": 3500,
      "maxCarry": 13,
      "friendshipPoints": 12,
      "recruit": {
        "exp": 158,
        "shards": 170
      }
    },
    "berry": {
      "id": 8,
      "quantity": 1
    },
    "ingredientChain": 317,
    "skill": 6,
    "evolution": {
      "next": [],
      "stage": 2,
      "previous": 316
    },
    "expType": 1,
    "eventType": 1
  },
  {
    "id": 333,
    "type": 10,
    "specialty": 1,
    "sleepType": 0,
    "stats": {
      "frequency": 4200,
      "maxCarry": 12,
      "friendshipPoints": 5,
      "recruit": {
        "exp": 8,
        "shards": 17
      }
    },
    "berry": {
      "id": 10,
      "quantity": 2
    },
    "ingredientChain": 334,
    "skill": 7,
    "evolution": {
      "next": [
        {
          "id": 334,
          "conditions": [
            {
              "type": "candy",
              "count": 40
            },
            {
              "type": "level",
              "level": 26
            }
          ]
        }
      ],
      "stage": 1,
      "previous": null
    },
    "expType": 1,
    "eventType": 1
  },
  {
    "id": 334,
    "type": 15,
    "specialty": 1,
    "sleepType": 4,
    "stats": {
      "frequency": 3700,
      "maxCarry": 14,
      "friendshipPoints": 12,
      "recruit": {
        "exp": 170,
        "shards": 306
      }
    },
    "berry": {
      "id": 15,
      "quantity": 2
    },
    "ingredientChain": 334,
    "skill": 7,
    "evolution": {
      "next": [],
      "stage": 2,
      "previous": 333
    },
    "expType": 1,
    "eventType": 1
  },
  {
    "id": 353,
    "type": 14,
    "specialty": 1,
    "sleepType": 4,
    "stats": {
      "frequency": 3900,
      "maxCarry": 11,
      "friendshipPoints": 5,
      "recruit": {
        "exp": 8,
        "shards": 17
      }
    },
    "berry": {
      "id": 14,
      "quantity": 2
    },
    "ingredientChain": 353,
    "skill": 5,
    "evolution": {
      "next": [
        {
          "id": 354,
          "conditions": [
            {
              "type": "candy",
              "count": 40
            },
            {
              "type": "level",
              "level": 28
            }
          ]
        }
      ],
      "stage": 1,
      "previous": null
    },
    "expType": 1,
    "eventType": 1
  },
  {
    "id": 354,
    "type": 14,
    "specialty": 1,
    "sleepType": 4,
    "stats": {
      "frequency": 2600,
      "maxCarry": 19,
      "friendshipPoints": 16,
      "recruit": {
        "exp": 186,
        "shards": 393
      }
    },
    "berry": {
      "id": 14,
      "quantity": 2
    },
    "ingredientChain": 353,
    "skill": 5,
    "evolution": {
      "next": [],
      "stage": 2,
      "previous": 353
    },
    "expType": 1,
    "eventType": 1
  },
  {
    "id": 359,
    "type": 16,
    "specialty": 2,
    "sleepType": 4,
    "stats": {
      "frequency": 3100,
      "maxCarry": 14,
      "friendshipPoints": 16,
      "recruit": {
        "exp": 263,
        "shards": 556
      }
    },
    "berry": {
      "id": 16,
      "quantity": 1
    },
    "ingredientChain": 359,
    "skill": 1,
    "evolution": {
      "next": [],
      "stage": 1,
      "previous": null
    },
    "expType": 1,
    "eventType": 1
  },
  {
    "id": 360,
    "type": 11,
    "specialty": 3,
    "sleepType": 0,
    "stats": {
      "frequency": 5800,
      "maxCarry": 7,
      "friendshipPoints": 5,
      "recruit": {
        "exp": 11,
        "shards": 12
      }
    },
    "berry": {
      "id": 11,
      "quantity": 1
    },
    "ingredientChain": 202,
    "skill": 4,
    "evolution": {
      "next": [
        {
          "id": 202,
          "conditions": [
            {
              "type": "candy",
              "count": 20
            },
            {
              "type": "level",
              "level": 11
            }
          ]
        }
      ],
      "stage": 1,
      "previous": null
    },
    "expType": 1,
    "eventType": 1
  },
  {
    "id": 363,
    "type": 6,
    "specialty": 1,
    "sleepType": 0,
    "stats": {
      "frequency": 5600,
      "maxCarry": 9,
      "friendshipPoints": 5,
      "recruit": {
        "exp": 11,
        "shards": 12
      }
    },
    "berry": {
      "id": 6,
      "quantity": 2
    },
    "ingredientChain": 365,
    "skill": 10,
    "evolution": {
      "next": [
        {
          "id": 364,
          "conditions": [
            {
              "type": "candy",
              "count": 40
            },
            {
              "type": "level",
              "level": 24
            }
          ]
        }
      ],
      "stage": 1,
      "previous": null
    },
    "expType": 1,
    "eventType": 1
  },
  {
    "id": 364,
    "type": 6,
    "specialty": 1,
    "sleepType": 0,
    "stats": {
      "frequency": 4000,
      "maxCarry": 13,
      "friendshipPoints": 12,
      "recruit": {
        "exp": 158,
        "shards": 170
      }
    },
    "berry": {
      "id": 6,
      "quantity": 2
    },
    "ingredientChain": 365,
    "skill": 10,
    "evolution": {
      "next": [
        {
          "id": 365,
          "conditions": [
            {
              "type": "candy",
              "count": 80
            },
            {
              "type": "level",
              "level": 33
            }
          ]
        }
      ],
      "stage": 2,
      "previous": 363
    },
    "expType": 1,
    "eventType": 1
  },
  {
    "id": 365,
    "type": 6,
    "specialty": 1,
    "sleepType": 0,
    "stats": {
      "frequency": 3000,
      "maxCarry": 18,
      "friendshipPoints": 20,
      "recruit": {
        "exp": 468,
        "shards": 586
      }
    },
    "berry": {
      "id": 6,
      "quantity": 2
    },
    "ingredientChain": 365,
    "skill": 10,
    "evolution": {
      "next": [],
      "stage": 3,
      "previous": 364
    },
    "expType": 1,
    "eventType": 1
  },
  {
    "id": 438,
    "type": 13,
    "specialty": 3,
    "sleepType": 0,
    "stats": {
      "frequency": 6300,
      "maxCarry": 8,
      "friendshipPoints": 5,
      "recruit": {
        "exp": 9,
        "shards": 16
      }
    },
    "berry": {
      "id": 13,
      "quantity": 1
    },
    "ingredientChain": 185,
    "skill": 2,
    "evolution": {
      "next": [
        {
          "id": 185,
          "conditions": [
            {
              "type": "candy",
              "count": 20
            },
            {
              "type": "level",
              "level": 12
            }
          ]
        }
      ],
      "stage": 1,
      "previous": null
    },
    "expType": 1,
    "eventType": 1
  },
  {
    "id": 439,
    "type": 11,
    "specialty": 2,
    "sleepType": 0,
    "stats": {
      "frequency": 4300,
      "maxCarry": 10,
      "friendshipPoints": 5,
      "recruit": {
        "exp": 7,
        "shards": 20
      }
    },
    "berry": {
      "id": 11,
      "quantity": 1
    },
    "ingredientChain": 439,
    "skill": 1,
    "evolution": {
      "next": [
        {
          "id": 122,
          "conditions": [
            {
              "type": "candy",
              "count": 40
            },
            {
              "type": "level",
              "level": 12
            }
          ]
        }
      ],
      "stage": 1,
      "previous": null
    },
    "expType": 1,
    "eventType": 1
  },
  {
    "id": 447,
    "type": 7,
    "specialty": 3,
    "sleepType": 0,
    "stats": {
      "frequency": 4200,
      "maxCarry": 9,
      "friendshipPoints": 5,
      "recruit": {
        "exp": 8,
        "shards": 17
      }
    },
    "berry": {
      "id": 7,
      "quantity": 1
    },
    "ingredientChain": 448,
    "skill": 3,
    "evolution": {
      "next": [
        {
          "id": 448,
          "conditions": [
            {
              "type": "candy",
              "count": 80
            },
            {
              "type": "sleepTime",
              "hours": 150.0
            },
            {
              "type": "timing",
              "startHour": 6,
              "endHour": 18
            }
          ]
        }
      ],
      "stage": 1,
      "previous": null
    },
    "expType": 1,
    "eventType": 1
  },
  {
    "id": 448,
    "type": 7,
    "specialty": 3,
    "sleepType": 0,
    "stats": {
      "frequency": 2700,
      "maxCarry": 14,
      "friendshipPoints": 20,
      "recruit": {
        "exp": 443,
        "shards": 1147
      }
    },
    "berry": {
      "id": 7,
      "quantity": 1
    },
    "ingredientChain": 448,
    "skill": 3,
    "evolution": {
      "next": [],
      "stage": 2,
      "previous": 447
    },
    "expType": 1,
    "eventType": 1
  },
  {
    "id": 453,
    "type": 8,
    "specialty": 2,
    "sleepType": 4,
    "stats": {
      "frequency": 5600,
      "maxCarry": 10,
      "friendshipPoints": 5,
      "recruit": {
        "exp": 9,
        "shards": 16
      }
    },
    "berry": {
      "id": 8,
      "quantity": 1
    },
    "ingredientChain": 454,
    "skill": 1,
    "evolution": {
      "next": [
        {
          "id": 454,
          "conditions": [
            {
              "type": "candy",
              "count": 40
            },
            {
              "type": "level",
              "level": 28
            }
          ]
        }
      ],
      "stage": 1,
      "previous": null
    },
    "expType": 1,
    "eventType": 1
  },
  {
    "id": 454,
    "type": 8,
    "specialty": 2,
    "sleepType": 4,
    "stats": {
      "frequency": 3400,
      "maxCarry": 14,
      "friendshipPoints": 12,
      "recruit": {
        "exp": 126,
        "shards": 227
      }
    },
    "berry": {
      "id": 8,
      "quantity": 1
    },
    "ingredientChain": 454,
    "skill": 1,
    "evolution": {
      "next": [],
      "stage": 2,
      "previous": 453
    },
    "expType": 1,
    "eventType": 1
  },
  {
    "id": 462,
    "type": 17,
    "specialty": 3,
    "sleepType": 0,
    "stats": {
      "frequency": 3100,
      "maxCarry": 13,
      "friendshipPoints": 22,
      "recruit": {
        "exp": 546,
        "shards": 1415
      }
    },
    "berry": {
      "id": 17,
      "quantity": 1
    },
    "ingredientChain": 462,
    "skill": 11,
    "evolution": {
      "next": [],
      "stage": 3,
      "previous": 82
    },
    "expType": 1,
    "eventType": 1
  },
  {
    "id": 468,
    "type": 18,
    "specialty": 3,
    "sleepType": 1,
    "stats": {
      "frequency": 2600,
      "maxCarry": 16,
      "friendshipPoints": 22,
      "recruit": {
        "exp": 722,
        "shards": 1300
      }
    },
    "berry": {
      "id": 18,
      "quantity": 1
    },
    "ingredientChain": 468,
    "skill": 13,
    "evolution": {
      "next": [],
      "stage": 3,
      "previous": 176
    },
    "expType": 1,
    "eventType": 1
  },
  {
    "id": 470,
    "type": 5,
    "specialty": 3,
    "sleepType": 4,
    "stats": {
      "frequency": 3000,
      "maxCarry": 13,
      "friendshipPoints": 20,
      "recruit": {
        "exp": 443,
        "shards": 1147
      }
    },
    "berry": {
      "id": 5,
      "quantity": 1
    },
    "ingredientChain": 470,
    "skill": 4,
    "evolution": {
      "next": [],
      "stage": 2,
      "previous": 133
    },
    "expType": 1,
    "eventType": 1
  },
  {
    "id": 471,
    "type": 6,
    "specialty": 3,
    "sleepType": 0,
    "stats": {
      "frequency": 3200,
      "maxCarry": 12,
      "friendshipPoints": 20,
      "recruit": {
        "exp": 443,
        "shards": 1147
      }
    },
    "berry": {
      "id": 6,
      "quantity": 1
    },
    "ingredientChain": 471,
    "skill": 11,
    "evolution": {
      "next": [],
      "stage": 2,
      "previous": 133
    },
    "expType": 1,
    "eventType": 1
  },
  {
    "id": 700,
    "type": 18,
    "specialty": 3,
    "sleepType": 1,
    "stats": {
      "frequency": 2600,
      "maxCarry": 15,
      "friendshipPoints": 20,
      "recruit": {
        "exp": 583,
        "shards": 894
      }
    },
    "berry": {
      "id": 18,
      "quantity": 1
    },
    "ingredientChain": 700,
    "skill": 8,
    "evolution": {
      "next": [],
      "stage": 2,
      "previous": 133
    },
    "expType": 1,
    "eventType": 1
  },
  {
    "id": 9001,
    "type": 4,
    "specialty": 1,
    "sleepType": 1,
    "stats": {
      "frequency": 2600,
      "maxCarry": 18,
      "friendshipPoints": 7,
      "recruit": {
        "exp": 7,
        "shards": 20
      }
    },
    "berry": {
      "id": 4,
      "quantity": 2
    },
    "ingredientChain": 26,
    "skill": 5,
    "evolution": {
      "next": [],
      "stage": 1,
      "previous": null
    },
    "expType": 1,
    "eventType": 201
  }
]